keras_model_cv/__init__.py
keras_model_cv/core.py
keras_model_cv-0.5.4.dist-info/METADATA
keras_model_cv-0.5.4.dist-info/WHEEL
keras_model_cv-0.5.4.dist-info/top_level.txt
keras_model_cv-0.5.4.dist-info/RECORD
