Metadata-Version: 2.1
Name: keras-model-cv
Version: 0.5.4
Summary: Cross-validation for keras models
Home-page: https://github.com/dubovikmaster/keras-model-cv
Author: Pavel Dubovik
Author-email: geometryk@gmail.com
License: MIT
Keywords: keras cross-validate,validation keras modelscross-validation
Platform: any
Requires-Dist: tensorflow (>=2.0)
Requires-Dist: scikit-learn
Requires-Dist: pandas
Requires-Dist: pyyaml
Requires-Dist: matplotlib
